TamClinet/__init__.py
TamClinet-0.0.1.dist-info/METADATA
TamClinet-0.0.1.dist-info/WHEEL
TamClinet-0.0.1.dist-info/top_level.txt
TamClinet-0.0.1.dist-info/RECORD
