Metadata-Version: 2.1
Name: TamClinet
Version: 0.0.1
Summary: This package can download tik tok video
Author: ibrahem
Author-email: ibrahemalkabby@gmail.com
Keywords: Tik,Tok,Tikdow,TikTokapi,download,TikTokdownload,TikTok-dl,vedio
Classifier: Development Status :: 1 - Planning
Classifier: Intended Audience :: Developers
Classifier: Programming Language :: Python :: 3
Classifier: Operating System :: Unix
Classifier: Operating System :: MacOS :: MacOS X
Classifier: Operating System :: Microsoft :: Windows
